cpp_protein_encoders/__init__.py
cpp_protein_encoders/cpp_ext/basic_encoders.cpp
cpp_protein_encoders/cpp_ext/basic_encoders.h
cpp_protein_encoders/cpp_ext/cpp_protein_encoders_ext.cpp
cpp_protein_encoders/cpp_ext/subsmat_tokenizer.cpp
cpp_protein_encoders/cpp_ext/subsmat_tokenizer.h
cpp_protein_encoders/cpp_ext/utilities.cpp
cpp_protein_encoders/cpp_ext/utilities.h
cpp_protein_encoders/cpp_protein_encoders_ext.cp39-win_amd64.pyd
cpp_protein_encoders/encoders.py
cpp_protein_encoders/protein_toolkits/__init__.py
cpp_protein_encoders/protein_toolkits/generate_pssm_loadfiles.py
cpp_protein_encoders/protein_toolkits/PFASUM62_raw.npy
cpp_protein_encoders/protein_toolkits/PFASUM62_standardized.npy
cpp_protein_encoders/protein_toolkits/PFASUM75_raw.npy
cpp_protein_encoders/protein_toolkits/PFASUM75_standardized.npy
cpp_protein_encoders/protein_toolkits/PFASUM85_raw.npy
cpp_protein_encoders/protein_toolkits/PFASUM85_standardized.npy
cpp_protein_encoders/protein_toolkits/PFASUM90_raw.npy
cpp_protein_encoders/protein_toolkits/PFASUM90_standardized.npy
cpp_protein_encoders/protein_toolkits/PFASUM95_raw.npy
cpp_protein_encoders/protein_toolkits/PFASUM95_standardized.npy
cpp_protein_encoders/protein_toolkits/pfasum_matrices/PFASUM100.mat
cpp_protein_encoders/protein_toolkits/pfasum_matrices/PFASUM11.mat
cpp_protein_encoders/protein_toolkits/pfasum_matrices/PFASUM12.mat
cpp_protein_encoders/protein_toolkits/pfasum_matrices/PFASUM13.mat
cpp_protein_encoders/protein_toolkits/pfasum_matrices/PFASUM14.mat
cpp_protein_encoders/protein_toolkits/pfasum_matrices/PFASUM15.mat
cpp_protein_encoders/protein_toolkits/pfasum_matrices/PFASUM16.mat
cpp_protein_encoders/protein_toolkits/pfasum_matrices/PFASUM17.mat
cpp_protein_encoders/protein_toolkits/pfasum_matrices/PFASUM18.mat
cpp_protein_encoders/protein_toolkits/pfasum_matrices/PFASUM19.mat
cpp_protein_encoders/protein_toolkits/pfasum_matrices/PFASUM20.mat
cpp_protein_encoders/protein_toolkits/pfasum_matrices/PFASUM21.mat
cpp_protein_encoders-0.0.1.dist-info/METADATA
cpp_protein_encoders-0.0.1.dist-info/WHEEL
cpp_protein_encoders-0.0.1.dist-info/licenses/LICENSE
cpp_protein_encoders-0.0.1.dist-info/RECORD
