Metadata-Version: 2.1
Name: cpp_protein_encoders
Version: 0.0.1
Summary: Fast Python-wrapped C++ basic encoders for protein sequences
Keywords: tokenizer,protein tokenizer,fast protein tokenizer,protein encoder,fast protein encoder
Author-Email: Jonathan Parkinson <jlparkinson1@gmail.com>
License: MIT License
Project-URL: Homepage, https://github.com/jlparki/cpp_protein_tokenizers
Project-URL: Documentation, https://github.com/jlparki/cpp_protein_tokenizers
Requires-Python: >=3.9
